{
  "slug": "dai-tiec-duoi-day-dai-duong-cung-voi-thuong-hieu-buffet-hai-san-cao-ca",
  "title": "Đại Tiệc Dưới Đáy Đại Dương Cùng Với Thương Hiệu Buffet Hải Sản Cao Cấp, Tươi Ngon Nhất Việt Nam",
  "date": "27/11/25",
  "blocks": [
    {
      "type": "paragraph",
      "align": "justify",
      "markdown": "**Buffet hải sản **luôn là lựa chọn tuyệt vời cho những buổi tiệc thịnh soạn, khi bạn muốn thưởng thức trọn vẹn hương vị tươi ngon, đa dạng của đại dương. Từ hải sản tươi sống nhập khẩu, lẩu nướng đến ẩm thực quốc tế, các thương hiệu lớn mang đến trải nghiệm đẳng cấp. **PATO** đã tổng hợp Top 7 thương hiệu buffet hải sản được săn đón nhất."
    },
    {
      "type": "heading",
      "level": 2,
      "id": null,
      "align": "justify",
      "markdown": "## **Bay Seafood Buffet**"
    },
    {
      "type": "paragraph",
      "align": "justify",
      "markdown": "**Bay Seafood Buffet **là chuỗi buffet hải sản cao cấp nổi tiếng với sự đa dạng của quầy line và hải sản tươi sống. Nhà hàng có không gian rộng lớn, thiết kế hiện đại, thường tọa lạc tại các vị trí đắc địa (như Lotte, Hồ Tây), phù hợp cho các buổi tiệc lớn. Món best seller là các loại hải sản tươi sống (ghẹ, tôm sú, hàu, ốc hương) được chế biến tại chỗ, cùng hơn 200 món Á – Âu khác như Sushi, Sashimi và Lẩu. Khoảng giá tham khảo dao động từ **450.000 VNĐ – 650.000 VNĐ/người**."
    },
    {
      "type": "image",
      "align": "center",
      "markdown": "![](//cdn.hstatic.net/1000275435/file/pato_anh_-_14_ab0e641497e74e96a4ad63156e91b1ab_1024x1024.png)",
      "src": "//cdn.hstatic.net/1000275435/file/pato_anh_-_14_ab0e641497e74e96a4ad63156e91b1ab_1024x1024.png"
    },
    {
      "type": "paragraph",
      "align": "center",
      "markdown": "*Quầy hải sản tươi sống hoành tráng và hơn 200 món Á - Âu tại Bay Seafood Buffet.*"
    },
    {
      "type": "heading",
      "level": 2,
      "id": null,
      "align": "justify",
      "markdown": "## **Buffet D'Maris**"
    },
    {
      "type": "paragraph",
      "align": "justify",
      "markdown": "**Buffet D'Maris **là thương hiệu buffet quốc tế cao cấp đến từ Hàn Quốc, nổi tiếng với sự hoành tráng và chất lượng hải sản nhập khẩu tươi ngon. Nhà hàng có không gian siêu rộng, sang trọng bậc nhất, thường đặt tại các TTTM lớn, rất phù hợp cho tiệc cưới, sự kiện. Món best seller là các món hải sản cao cấp (cua, tôm, ghẹ) được chế biến đa dạng, Sushi/Sashimi tươi rói, cùng với khu vực ẩm thực Á, Âu, và món tráng miệng phong phú. Khoảng giá tham khảo thuộc phân khúc cao cấp, từ **480.000 VNĐ – 780.000 VNĐ/người**."
    },
    {
      "type": "image",
      "align": "center",
      "markdown": "![](//cdn.hstatic.net/1000275435/file/pato_anh_-_15_a56c5fe6fa924608af06203960b6d109_1024x1024.png)",
      "src": "//cdn.hstatic.net/1000275435/file/pato_anh_-_15_a56c5fe6fa924608af06203960b6d109_1024x1024.png"
    },
    {
      "type": "paragraph",
      "align": "center",
      "markdown": "*Buffet quốc tế hoành tráng, đẳng cấp 5 sao với hải sản tươi ngon tại D'Maris.*"
    },
    {
      "type": "paragraph",
      "align": "justify",
      "markdown": "***>>> Muốn thưởng thức những bữa tiệc Buffet đầy sang trọng liên hệ ngay với [PATO](http://pato.com.vn) qua hotline [1900 2280 ](tel:19002280 )để được hỗ trợ tư vấn nhanh chóng nhất***"
    },
    {
      "type": "heading",
      "level": 2,
      "id": null,
      "align": "justify",
      "markdown": "## **Buffet Hải Sản Cửu Vân Long**"
    },
    {
      "type": "paragraph",
      "align": "justify",
      "markdown": "**Buffet Hải Sản Cửu Vân Long** là thương hiệu kết hợp giữa Buffet Hải Sản và Dimsum Hong Kong, mang lại sự độc đáo trong thực đơn. Nhà hàng có không gian hiện đại, sang trọng, với phong cách Trung Hoa tinh tế. Món best seller là sự kết hợp của Hải sản tươi sống được chế biến tại chỗ và các món Dimsum thủ công trứ danh (Há cảo, Bánh bao Kim Sa). Đây là lựa chọn tuyệt vời cho những ai yêu thích cả ẩm thực biển và các món Hoa truyền thống. Khoảng giá tham khảo dao động từ **350.000 VNĐ – 550.000 VNĐ/người.**"
    },
    {
      "type": "image",
      "align": "center",
      "markdown": "![](//cdn.hstatic.net/1000275435/file/pato_anh_-_16_5ef6005d5df043e5a5d0b54f4d29dfae_1024x1024.png)",
      "src": "//cdn.hstatic.net/1000275435/file/pato_anh_-_16_5ef6005d5df043e5a5d0b54f4d29dfae_1024x1024.png"
    },
    {
      "type": "paragraph",
      "align": "center",
      "markdown": "*Hải sản tươi ngon và Dimsum Hong Kong tinh tế trong cùng một bữa tiệc buffet tại Cửu Vân Long.*"
    },
    {
      "type": "heading",
      "level": 2,
      "id": null,
      "align": "justify",
      "markdown": "## **Buffet Poseidon**"
    },
    {
      "type": "paragraph",
      "align": "justify",
      "markdown": "**Buffet Poseidon** là thương hiệu buffet hải sản và lẩu nướng nổi tiếng với chất lượng ổn định và thực đơn phong phú. Nhà hàng có không gian rộng rãi, thoáng đãng, phù hợp cho mọi đối tượng khách hàng. Món best seller là quầy hải sản tươi sống (Bề bề, sò dương, ốc gai), các món lẩu nướng đa dạng, và các món Á – Âu khác. Poseidon thường có các gói Set Menu hấp dẫn cho khách hàng. Khoảng giá tham khảo từ** 358.000 VNĐ – 568.000 VNĐ/người.**"
    },
    {
      "type": "image",
      "align": "center",
      "markdown": "![](//cdn.hstatic.net/1000275435/file/pato_anh_-_17_38e59dedb44a46ebb8bfd7000382f246_1024x1024.png)",
      "src": "//cdn.hstatic.net/1000275435/file/pato_anh_-_17_38e59dedb44a46ebb8bfd7000382f246_1024x1024.png"
    },
    {
      "type": "paragraph",
      "align": "center",
      "markdown": "*Quầy hải sản tươi rói và đa dạng tại Buffet Poseidon, thỏa mãn tín đồ ẩm thực biển.*"
    },
    {
      "type": "heading",
      "level": 2,
      "id": null,
      "align": "justify",
      "markdown": "## **Maison Sen Buffet**"
    },
    {
      "type": "paragraph",
      "align": "justify",
      "markdown": "**Maison Sen Buffet **là nhà hàng buffet quốc tế cao cấp với kiến trúc Indochine lộng lẫy và sang trọng. Nhà hàng nổi bật với không gian đẹp như cung điện, lý tưởng cho những dịp kỷ niệm. Món best seller là sự kết hợp của ẩm thực Việt Nam tinh hoa, các món Âu – Á, và quầy hải sản tươi sống chất lượng cao (tôm, hàu, ghẹ). Maison Sen mang lại trải nghiệm ẩm thực đẳng cấp. Khoảng giá tham khảo từ** 390.000 VNĐ – 580.000 VNĐ/người.**"
    },
    {
      "type": "image",
      "align": "center",
      "markdown": "![](//cdn.hstatic.net/1000275435/file/pato_anh_-_18_511c3983c10b4605a19bc6eb3fda90f3_1024x1024.png)",
      "src": "//cdn.hstatic.net/1000275435/file/pato_anh_-_18_511c3983c10b4605a19bc6eb3fda90f3_1024x1024.png"
    },
    {
      "type": "paragraph",
      "align": "center",
      "markdown": "*Maison Sen – Buffet Indochine sang trọng với hải sản và ẩm thực tinh hoa Á - Âu.*"
    },
    {
      "type": "paragraph",
      "align": "justify",
      "markdown": "***>>> Xem ngay: [Điểm Danh 7 Địa Điểm Hải Sản Buffet Hà Nội Được Yêu Thích Nhất Hiện Nay](https://pato.com.vn/blogs/blog-pato/diem-danh-7-dia-diem-hai-san-buffet-ha-noi-duoc-yeu-thich-nhat-hien-na) ***"
    },
    {
      "type": "heading",
      "level": 2,
      "id": null,
      "align": "justify",
      "markdown": "## **Buffet lẩu nướng hải sản Chef Dzung**"
    },
    {
      "type": "paragraph",
      "align": "justify",
      "markdown": "**Buffet lẩu nướng hải sản Chef Dzung** là thương hiệu chuyên về lẩu nướng hải sản với chất lượng được đánh giá cao. Nhà hàng có không gian rộng, hiện đại, phục vụ theo hình thức buffet quầy line. Món best seller là các loại hải sản tươi sống (cua, ghẹ, tôm càng) được chế biến tại chỗ, cùng khu vực nướng và lẩu tự chọn với các loại thịt bò hảo hạng. Chef Dzung cam kết về chất lượng nguyên liệu tươi ngon. Khoảng giá tham khảo từ **400.000 VNĐ – 500.000 VNĐ/người.**"
    },
    {
      "type": "image",
      "align": "center",
      "markdown": "![](//cdn.hstatic.net/1000275435/file/pato_anh_-_19_f0b9a038681a4fccb83b8e36b8cb4559_1024x1024.png)",
      "src": "//cdn.hstatic.net/1000275435/file/pato_anh_-_19_f0b9a038681a4fccb83b8e36b8cb4559_1024x1024.png"
    },
    {
      "type": "paragraph",
      "align": "center",
      "markdown": "*Thưởng thức hải sản tươi sống và lẩu nướng chất lượng cao tại Buffet Chef Dzung.*"
    },
    {
      "type": "paragraph",
      "align": "justify",
      "markdown": "Từ sự sang trọng, hoành tráng của D'Maris và Maison Sen, đến sự tươi ngon của Bay Seafood Buffet và Chef Dzung, danh sách Top 7 thương hiệu** buffet hải sản** này đã mang đến những lựa chọn tuyệt vời cho mọi tín đồ ẩm thực biển."
    }
  ],
  "related_articles": {
    "title": "Các bài viết liên quan",
    "items": [
      {
        "title": "Top 5 quán hải sản ngon Sài Gòn 2026: Tươi rói, đậm đà, \"oanh tạc\" mọi buổi nhậu",
        "url": "/blogs/blog-pato/top-5-quan-hai-san-ngon-sai-gon-2026-tuoi-roi-dam-da-oanh-tac-moi"
      },
      {
        "title": "Top 5 mỹ vị Gia Lâm: Từ đồ Nhật thượng hạng đến lẩu Thái cay nồng chuẩn vị",
        "url": "/blogs/blog-pato/top-5-my-vi-gia-lam-tu-do-nhat-thuong-hang-den-lau-thai-cay-nong-chua"
      },
      {
        "title": "Top Những Quán Nhậu Chất Đét, \"Bén Mồi\" Không Thể Bỏ Qua Tại Hà Nội",
        "url": "/blogs/blog-pato/top-nhung-quan-nhau-chat-det-ben-moi-khong-the-bo-qua-tai-ha-noi"
      },
      {
        "title": "Top Những Quán Gà Ngon Nức Tiếng Không Thể Bỏ Lỡ Tại Hà Nội",
        "url": "/blogs/blog-pato/top-nhung-quan-ga-ngon-nuc-tieng-khong-the-bo-lo-tai-ha-noi"
      },
      {
        "title": "Top 5 Quán Sushi Và Ẩm Thực Nhật Bản Đáng Thử Nhất Tại Hà Nội",
        "url": "/blogs/blog-pato/top-5-quan-sushi-va-am-thuc-nhat-ban-dang-thu-nhat-tai-ha-noi"
      },
      {
        "title": "Top 5 \"thiên đường\" đồ Thái quận Cầu Giấy: Vị chuẩn xứ Chùa Vàng, ngon quên lối về!",
        "url": "/blogs/blog-pato/top-5-thien-duong-do-thai-quan-cau-giay-vi-chuan-xu-chua-vang-ngon"
      }
    ]
  }
}