{
  "slug": "goi-y-thuc-don-mam-com-gia-dinh-mien-bac-hap-dan-du-dinh-duong",
  "title": "Gợi ý thực đơn mâm cơm gia đình miền Bắc hấp dẫn, đủ dinh dưỡng",
  "date": "09/07/22",
  "blocks": [
    {
      "type": "image",
      "align": "center",
      "markdown": "![](//file.hstatic.net/1000275435/file/mam-com-gia-dinh-mien-bac_6__692ce0da314d468ebc9078f4e72b18d8_grande.png)",
      "src": "//file.hstatic.net/1000275435/file/mam-com-gia-dinh-mien-bac_6__692ce0da314d468ebc9078f4e72b18d8_grande.png"
    },
    {
      "type": "paragraph",
      "align": "justify",
      "markdown": "Miền Bắc là địa phương nổi tiếng với nhiều món ăn đậm đà hương vị. **Mâm cơm miền Bắc** cũng rất đa dạng, mỗi món đều có cách chế biến và cung cấp hàm lượng chất dinh dưỡng riêng cho các thành viên trong gia đình. Trong bài viết này, [**PATO**](https://pato.com.vn/) sẽ gợi ý cho bạn những **mâm cơm gia đình miền Bắc **với đầy đủ các món: chiên, xào, tráng miệng,..."
    },
    {
      "type": "heading",
      "level": 2,
      "id": null,
      "align": "justify",
      "markdown": "## Thực đơn cầu kỳ, bắt mắt"
    },
    {
      "type": "paragraph",
      "align": "justify",
      "markdown": "Mâm cơm bao gồm các món: Gỏi tôm mực kiểu Thái, chân giò hầm đậu phộng, trứng cuộn rau củ, canh cà chua, mận Hà Nội là món tráng miệng."
    },
    {
      "type": "paragraph",
      "align": "justify",
      "markdown": "- Món gỏi tôm mực Thái Lan có vị chua chua, cay cay thơm ngon với sự thanh mát ngọt tự nhiên của tôm và mực là sự lựa chọn phù hợp cho những bữa cơm dịp cuối tuần."
    },
    {
      "type": "paragraph",
      "align": "justify",
      "markdown": "- Chân giò hầm đậu phộng: chân giò dai dai cùng đậu phộng thơm mềm, không chỉ là món ăn dinh dưỡng mà còn khiến chúng ta phải xuýt xoa trước hương vị thơm ngon cùng màu sắc bắt mắt."
    },
    {
      "type": "paragraph",
      "align": "justify",
      "markdown": "- Trứng cuộn rau củ là món cực kỳ thơm ngon và dễ làm. Trứng chín mềm lại thêm tròn vị từ các loại rau củ ngon ngọt sẽ là một món ăn thích hợp cho cả gia đình."
    },
    {
      "type": "paragraph",
      "align": "justify",
      "markdown": "- Canh là một món không thể thiếu trong bữa cơm gia đình. Một tô canh cà chua trứng vừa đơn giản, lại còn dễ ăn với phần nước dùng chua nhẹ, được nêm nếm vừa phải sẽ giúp bữa cơm gia đình thêm tròn vị."
    },
    {
      "type": "image",
      "align": "center",
      "markdown": "![](//file.hstatic.net/1000275435/file/mam-com-gia-dinh-mien-bac_3__014a09a797ab42eb8a3523ee9ff00d65_grande.png)",
      "src": "//file.hstatic.net/1000275435/file/mam-com-gia-dinh-mien-bac_3__014a09a797ab42eb8a3523ee9ff00d65_grande.png"
    },
    {
      "type": "paragraph",
      "align": "center",
      "markdown": "***Thực đơn món ăn miền Bắc ****cầu kỳ, bắt mắt *"
    },
    {
      "type": "heading",
      "level": 2,
      "id": null,
      "align": "justify",
      "markdown": "## Thực đơn thanh mát tròn vị"
    },
    {
      "type": "paragraph",
      "align": "justify",
      "markdown": "**Mâm cơm miền Bắc **gồm các món: canh mồng tơi thịt băm, sườn xào chua ngọt, trứng cút chiên sả ớt, bưởi tráng miệng."
    },
    {
      "type": "paragraph",
      "align": "justify",
      "markdown": "- Canh mồng tơi thịt băm: Là một món canh đơn giản, dễ nấu có vị ngọt ngon, thanh mát phù hợp mâm cơm gia đình vào mùa hè. Vị ngọt thanh của nước dùng, thịt thơm cùng với rau mồng tơi hòa quyện chắc chắn sẽ là món canh đưa cơm hoàn hảo."
    },
    {
      "type": "paragraph",
      "align": "justify",
      "markdown": "- Sườn xào chua ngọt: Đặc trưng của món ăn này là miếng sườn dai mềm, nước sốt chua chua, ngọt ngọt, đậm đà."
    },
    {
      "type": "paragraph",
      "align": "justify",
      "markdown": "- Trứng cút chiên sả ớt: Nguyên liệu để chế biến món ăn này khá đơn giản và quen thuộc như: trứng cút, sả, ớt thơm ngon với vị chua cay nhẹ."
    },
    {
      "type": "image",
      "align": "center",
      "markdown": "![](//file.hstatic.net/1000275435/file/mam-com-gia-dinh-mien-bac_deda71813ae64e7992f739ff4ef95aec_grande.png)",
      "src": "//file.hstatic.net/1000275435/file/mam-com-gia-dinh-mien-bac_deda71813ae64e7992f739ff4ef95aec_grande.png"
    },
    {
      "type": "paragraph",
      "align": "center",
      "markdown": "***Mâm cơm gia đình miền Bắc**** thanh mát, tròn vị *"
    },
    {
      "type": "heading",
      "level": 2,
      "id": null,
      "align": "justify",
      "markdown": "## Thực đơn đơn giản, đủ chất"
    },
    {
      "type": "paragraph",
      "align": "justify",
      "markdown": "Gồm các món: Thịt kho trứng cút, canh ngao nấu chua, mướp xào lòng gà, chè đậu xanh nha đam."
    },
    {
      "type": "paragraph",
      "align": "justify",
      "markdown": "- Thịt kho trứng cút: Với nguyên liệu quen thuộc như thịt heo và trứng cút là chúng ta có thể chế biến một món ăn thơm ngon với thịt heo đậm vị, mềm ngon đi kèm với trứng cút bùi bùi."
    },
    {
      "type": "paragraph",
      "align": "justify",
      "markdown": "- Canh ngao nấu chua: Có vị chua nhẹ kết hợp cùng vị cay và thơm nồng của sả và ớt mang đến hương vị rất lôi cuốn giải ngấy cho bữa thịt kho."
    },
    {
      "type": "paragraph",
      "align": "justify",
      "markdown": "- Lòng gà xào mướp: với màu sắc xanh mướt bắt mắt. Khi ăn sẽ cảm nhận được hương vị ngọt ngon từ mướp hòa quyện với miếng lòng gà giòn ngon, rất thích hợp để ăn kèm với cơm nóng."
    },
    {
      "type": "paragraph",
      "align": "justify",
      "markdown": "- Chè đậu xanh nha đam với những miếng nha đam giòn giòn hòa quyện cùng vị thơm bùi của đậu xanh và nước cốt dừa béo ngậy rất phù hợp với ngày nóng dùng để giải nhiệt và thanh lọc cơ thể."
    },
    {
      "type": "image",
      "align": "center",
      "markdown": "![](//file.hstatic.net/1000275435/file/mam-com-gia-dinh-mien-bac_1__36a86b7d6ac141f2ba9c2d2f3e4c7a0a_grande.png)",
      "src": "//file.hstatic.net/1000275435/file/mam-com-gia-dinh-mien-bac_1__36a86b7d6ac141f2ba9c2d2f3e4c7a0a_grande.png"
    },
    {
      "type": "paragraph",
      "align": "center",
      "markdown": "***Thực đơn mâm cơm gia đình miền Bắc**** đơn giản, đủ chất *"
    },
    {
      "type": "heading",
      "level": 2,
      "id": null,
      "align": "justify",
      "markdown": "## Thực đơn dễ nấu"
    },
    {
      "type": "paragraph",
      "align": "justify",
      "markdown": "Thịt ba chỉ chiên sả, canh cua rau đay, nộm rau muống, vải tráng miệng."
    },
    {
      "type": "paragraph",
      "align": "justify",
      "markdown": "- Thịt ba chỉ chiên là món ăn khá quen thuộc với nhiều gia đình. Thịt chiên có hương thơm lừng của sả, khi ăn sẽ cảm nhận được mùi vị đậm đà của thịt chiên, bên ngoài giòn ngon, bên trong chín mềm."
    },
    {
      "type": "paragraph",
      "align": "justify",
      "markdown": "- Canh cua rau đay thanh mát, hòa quyện cùng vị ngọt thơm rất phù hợp trong **mâm cơm miền Bắc **ngày nắng nóng."
    },
    {
      "type": "paragraph",
      "align": "justify",
      "markdown": "- Nộm rau muống sẽ là một nét độc đáo với vị giòn tự nhiên và chua ngọt cũng là một trong những món ăn dễ chế biến. Các chị em có thể làm cho cả gia đình cùng thưởng thức."
    },
    {
      "type": "image",
      "align": "center",
      "markdown": "![](//file.hstatic.net/1000275435/file/mam-com-gia-dinh-mien-bac_4__4cda31ffd62146a58798d87db5395254_grande.png)",
      "src": "//file.hstatic.net/1000275435/file/mam-com-gia-dinh-mien-bac_4__4cda31ffd62146a58798d87db5395254_grande.png"
    },
    {
      "type": "paragraph",
      "align": "center",
      "markdown": "***Mâm cơm miền Bắc ****dễ chế biến *"
    },
    {
      "type": "heading",
      "level": 2,
      "id": null,
      "align": "justify",
      "markdown": "## Thực đơn đổi vị mới lạ"
    },
    {
      "type": "paragraph",
      "align": "justify",
      "markdown": "Cá chép rán giòn, giò thủ, canh gân bò nấu dưa chua, thạch chanh leo."
    },
    {
      "type": "paragraph",
      "align": "justify",
      "markdown": "- Cá chép rán giòn: Để đổi vị cho bữa cơm gia đình thì món cá chép rán giòn là một sự lựa chọn hợp lý. Một miếng thịt cá thanh ngọt cuộn cùng với rau sống, ít lát dưa leo và dứa cắt mỏng, sau đó cuộn chặt lại bằng bánh tráng dai ngon cùng nước chấm chua ngọt sẽ là món ăn đưa cơm lạ miệng."
    },
    {
      "type": "paragraph",
      "align": "justify",
      "markdown": "- Giò thủ: có vị giòn sần sật của mộc nhĩ, nấm đông cô, thịt chặt nhờ ép chắc tay, ăn vào sẽ cảm nhận ngay được vị cay cay tê tê, thơm nựng đầu lưỡi."
    },
    {
      "type": "paragraph",
      "align": "justify",
      "markdown": "- Gân bò chua cay: Gân bò mềm thơm, thấm vị, hòa cùng vị cay tưng bừng của vị lẩu thái chua cay sẽ là món ăn tuyệt hảo cho bữa cơm gia đình."
    },
    {
      "type": "image",
      "align": "center",
      "markdown": "![](//file.hstatic.net/1000275435/file/mam-com-gia-dinh-mien-bac_5__b7e8888fee1646ddba02968c87b2ffbd_grande.png)",
      "src": "//file.hstatic.net/1000275435/file/mam-com-gia-dinh-mien-bac_5__b7e8888fee1646ddba02968c87b2ffbd_grande.png"
    },
    {
      "type": "paragraph",
      "align": "center",
      "markdown": "***Món ăn miền bắc**** đổi vị mới lạ *"
    },
    {
      "type": "heading",
      "level": 2,
      "id": null,
      "align": "justify",
      "markdown": "## Thực đơn đậm đà hương vị miền Bắc"
    },
    {
      "type": "paragraph",
      "align": "justify",
      "markdown": "Tôm rang mặn ngọt, canh sấu thịt băm, thịt gà luộc, cải ngọt xào tôm, lê tráng miệng."
    },
    {
      "type": "paragraph",
      "align": "justify",
      "markdown": "- Tôm rang là một trong những món ăn quen thuộc trong **mâm cơm gia đình miền Bắc**. Món tôm rang tỏi đặc trưng bởi vị mặn ngọt hài hoà cùng mùi thơm lừng của tỏi."
    },
    {
      "type": "paragraph",
      "align": "justify",
      "markdown": "- Canh sấu thịt băm với vị chua chua từ sấu và thịt băm mềm ngọt vô cùng hấp dẫn - chắc chắn sẽ là một món canh thơm ngon mà bạn phải thử trổ tài cho cả gia đình cùng thưởng thức."
    },
    {
      "type": "paragraph",
      "align": "justify",
      "markdown": "- Gà luộc là món ăn khá phổ biến và được yêu thích trong mỗi gia đình Việt bởi giữ được vị ngọt của gà và cách chế biến cũng không quá phức tạp."
    },
    {
      "type": "paragraph",
      "align": "justify",
      "markdown": "- Cải ngọt xào tôm trông rất bắt mắt và thơm ngon với hương vị ngọt, mềm đặc trưng của tôm, các nguyên liệu được xào rất hài hòa vừa ăn và bắt vị. Đảm bảo đây sẽ là món xào siêu hao cơm trong mỗi gia đình."
    },
    {
      "type": "image",
      "align": "center",
      "markdown": "![](//file.hstatic.net/1000275435/file/mam-com-gia-dinh-mien-bac_2__e99f84f76a7c4d418a9ead4f69206be3_grande.png)",
      "src": "//file.hstatic.net/1000275435/file/mam-com-gia-dinh-mien-bac_2__e99f84f76a7c4d418a9ead4f69206be3_grande.png"
    },
    {
      "type": "paragraph",
      "align": "center",
      "markdown": "*Đậm đà ****hương vị mâm cơm miền Bắc ***"
    },
    {
      "type": "paragraph",
      "align": "justify",
      "markdown": "***Xem thêm:**** Top những* [***nhà hàng món Bắc***](https://pato.com.vn/search?q=filter=((tag:product=url_cha_H%C3%A0%20N%E1%BB%99i)&&(tag:product=loaihinh_M%C3%B3n%20%C4%83n%20mi%E1%BB%81n%20B%E1%BA%AFc_ch%C3%ADnh)))* không thể bỏ qua tại Hà Nội. *"
    },
    {
      "type": "paragraph",
      "align": "justify",
      "markdown": "Trên đây là thực đơn **mâm cơm gia đình miền Bắc **hấp dẫn được [**PATO**](https://pato.com.vn/) chia sẻ đến bạn. Theo dõi thêm công thức nấu món ngon tiếp theo tại blog [**PATO**](https://pato.com.vn/). Nếu bạn muốn thưởng thức ngay món ăn miền Bắc chuẩn vị, hãy liên hệ đường dây nóng [**1900.2280**](tel:1900.2280) để được [**PATO**](https://pato.com.vn/) hỗ trợ đặt bàn và ship đồ ăn với nhiều ưu đãi hấp dẫn."
    }
  ],
  "related_articles": {
    "title": "Các bài viết liên quan",
    "items": [
      {
        "title": "Ẩm thực miền Trung độc đáo - hấp dẫn - mới lạ bạn đã biết chưa?",
        "url": "/blogs/am-thuc-3-mien/am-thuc-mien-trung-doc-dao-hap-dan"
      },
      {
        "title": "Top 10+ đặc sản Cao Bằng ngon - bổ - rẻ thích hợp mua về làm quà",
        "url": "/blogs/am-thuc-3-mien/top-10-dac-san-cao-bang"
      },
      {
        "title": "Khám phá văn hóa ẩm thực Tây Bắc cùng các món đặc sản núi rừng",
        "url": "/blogs/am-thuc-3-mien/van-hoa-am-thuc-tay-bac-va-cac-mon-dac-san"
      },
      {
        "title": "Top 7 món ngon từ cốm Hà Nội mà nhất định bạn không thể bỏ qua",
        "url": "/blogs/am-thuc-3-mien/top-7-mon-ngon-tu-com-ha-noi"
      },
      {
        "title": "Cách làm cơm tấm sườn bì chả thơm ngon chuẩn vị bạn nên biết",
        "url": "/blogs/am-thuc-3-mien/cach-lam-com-tam-suon-bi-cha"
      },
      {
        "title": "Bật mí các tips giúp bạn đổ bánh xèo giòn ngon như ngoài hàng",
        "url": "/blogs/am-thuc-3-mien/tips-do-banh-xeo-gion-ngon"
      }
    ]
  }
}