{
  "slug": "nha-hang-nhat-ngon-bo-re-nhat-ha-noi",
  "title": "Điểm Danh Top 10 Nhà Hàng Nhật Ngon Bổ Rẻ Nhất Hà Nội",
  "date": "22/02/21",
  "blocks": [
    {
      "type": "image",
      "align": "center",
      "markdown": "![](//file.hstatic.net/1000275435/file/top-10-nha-hang-nhat-ngon-bo-re-tai-ha-noi_7d3dfa612c544f138a7b4bb31f975b23_grande.jpg)",
      "src": "//file.hstatic.net/1000275435/file/top-10-nha-hang-nhat-ngon-bo-re-tai-ha-noi_7d3dfa612c544f138a7b4bb31f975b23_grande.jpg"
    },
    {
      "type": "paragraph",
      "align": "justify",
      "markdown": "Ẩm thực Nhật Bản từ lâu đã có một chất riêng của mình, vô cùng tinh tế tạo nên sắc thái vô cùng sang trọng mà khó có nền ẩm thực nào sánh được. Hãy cùng PATO điểm qua 10 **Nhà Hàng Nhật** chuẩn hương vị truyền thống nhưng giá thành thì vô cùng “Hạt dẻ” nhé!"
    },
    {
      "type": "heading",
      "level": 2,
      "id": null,
      "align": "justify",
      "markdown": "## **Kamon **"
    },
    {
      "type": "paragraph",
      "align": "justify",
      "markdown": "Tọa lạc tại **số 104 A5 Vạn Phúc, Ngọc Khánh**, Nhà hàng Kamon sở hữu một không gian đậm đà hơi thở Nhật Bản. Mỗi món ăn tại Kamon mang một hương vị rất riêng với cách chế biến độc đáo đã tạo nên một thực đơn khiến thực khách chẳng thể chối từ: Thịt nướng, Cá nướng, Mì udon, Soba, Ramen, Lẩu, ..."
    },
    {
      "type": "paragraph",
      "align": "justify",
      "markdown": "Ngoài ra, đến với Kamon, thực khách còn có cơ hội tận hưởng không gian ấm cúng, thoải mái, gần gũi với lối phục vụ chuyên nghiệp. Đặc biệt với mức giá chỉ từ 120.000 - 150.000đ/người, Nhà hàng thực sự là gợi ý lý tưởng cho những buổi gặp mặt gia đình, bạn bè hay hẹn hò lãng mạn."
    },
    {
      "type": "image",
      "align": "center",
      "markdown": "![](//file.hstatic.net/1000275435/file/nha-hang-nhat-ngon-kamon_e7adeeb63b404107ad411e4080cf216b_grande.jpg)",
      "src": "//file.hstatic.net/1000275435/file/nha-hang-nhat-ngon-kamon_e7adeeb63b404107ad411e4080cf216b_grande.jpg"
    },
    {
      "type": "paragraph",
      "align": "justify",
      "markdown": "**>>> Đặt bàn ngay tại: ****[Kamon](kamon-104-a5-van-phuc)**"
    },
    {
      "type": "heading",
      "level": 2,
      "id": null,
      "align": "justify",
      "markdown": "## **Ganeya**"
    },
    {
      "type": "paragraph",
      "align": "justify",
      "markdown": "Với mức giá vô cùng hợp lý chỉ từ 100.000 - 200.000đ/người, khi đến nhà hàng thực khách sẽ được thưởng thức hàng loạt món ăn đậm chất** ẩm thực Nhật** **Bản**: Sashimi cá nóc, Sashimi cá ngừ, Sashimi bạch tuộc, Sashimi cá trắng, Sashimi cá khế, Sashimi cá hồi, Sashimi bụng cá hồi, Sashimi sò đỏ**,...**"
    },
    {
      "type": "paragraph",
      "align": "justify",
      "markdown": "Ganeya tọa lạc tại số 41 Trần Quốc Toản, Hoàn Kiếm, Nhà hàng được thiết kế vô cùng thoáng mát, thoải mái. Đặc biệt bố cục bài trí chính của nhà hàng chính là theo chất Nhật, từ những chiêc bàn, những viên đá cuội, những bức tranh cũng vô cùng Nhật Bản."
    },
    {
      "type": "image",
      "align": "center",
      "markdown": "![](//file.hstatic.net/1000275435/file/nha-hang-nhat-ganeya_bebde27ca10d402b9c55aada54413027_grande.jpg)",
      "src": "//file.hstatic.net/1000275435/file/nha-hang-nhat-ganeya_bebde27ca10d402b9c55aada54413027_grande.jpg"
    },
    {
      "type": "paragraph",
      "align": "justify",
      "markdown": "**>>> Đặt bàn ngay tại: ****[Ganeya](ganeya-41-tran-quoc-toan)**"
    },
    {
      "type": "heading",
      "level": 2,
      "id": null,
      "align": "justify",
      "markdown": "## **Nhật Bản Vạn Phúc**"
    },
    {
      "type": "paragraph",
      "align": "justify",
      "markdown": "Kể từ khi ra đời, nơi đây đã trở thành cái tên vô cùng quen thuộc mỗi khi giới sành ăn nhắc đến **nhà hàng Nhật Bản**. Khi thưởng món nơi đây, thực khách sẽ được tận hưởng không gian vô cùng thoáng mát sạch sẽ."
    },
    {
      "type": "paragraph",
      "align": "justify",
      "markdown": "Tọa lạc tại số 26 Đào Tấn, thực khách sẽ được thưởng thức những món ăn truyền thống của Nhật chuẩn vị. Đặc biệt với mức giá chỉ rơi vào 54.000 - 200.000đ/người, Nhà hàng Nhật Bản Vạn Phúc là lựa chọn hoàn hảo cho các buổi liên hoan, gặp mặt, hẹn hò cùng gia đình, bạn bè và đồng nghiệp."
    },
    {
      "type": "image",
      "align": "center",
      "markdown": "![](//file.hstatic.net/1000275435/file/nhat-ban-van-phuc-so-26-dao-tan-ba-dinh-ha-noi_f1a1570d680b465facece19f2318f85f_grande.jpg)",
      "src": "//file.hstatic.net/1000275435/file/nhat-ban-van-phuc-so-26-dao-tan-ba-dinh-ha-noi_f1a1570d680b465facece19f2318f85f_grande.jpg"
    },
    {
      "type": "paragraph",
      "align": "justify",
      "markdown": "**>>> Đặt bàn ngay tại: ****[Nhật Bản Vạn Phúc](nhat-ban-van-phuc-26-dao-tan)**"
    },
    {
      "type": "heading",
      "level": 2,
      "id": null,
      "align": "justify",
      "markdown": "## **Trạm Sushi**"
    },
    {
      "type": "paragraph",
      "align": "justify",
      "markdown": "Trạm Sushi là nhà hàng chuyên phục vụ món Nhật và là một trong những Nhà hàng được đánh giá cao tại quận Đống Đa. Tọa lạc tại số 17 ngõ 19 Trần Quang Diệu, Đống Đa, Hà Nội, Trạm Sushi là một gợi ý không thể bỏ qua mỗi khi có dịp không chỉ bởi ẩm thực độc đáo mà còn bởi không gian lịch sự, hiện đại."
    },
    {
      "type": "paragraph",
      "align": "justify",
      "markdown": "Với mức giá khoảng 150.000 - 200.000đ/người, khi đến nhà hàng thực khách sẽ được thưởng thức hàng loạt món ăn hấp dẫn đã làm nên tên tuổi của Nhà hàng như: **Sushi, Sashimi**, Cơm Nhật, Cuộn Maki và ác món ăn kèm như: Soup, Salad, Snack, các set tổng hợp không kém phần hấp dẫn. Tất cả được tạo nên từ những nguyên liệu sạch và chất lượng, nhằm đảm bảo hương vị cho món ăn cũng như bảo vệ sức khỏe của thực khách."
    },
    {
      "type": "image",
      "align": "center",
      "markdown": "![](//file.hstatic.net/1000275435/file/tram-sushi-so-17-ngo-19-tran-quang-dieu-ha-noi_6f7e40ac2d5b406788a22018d7af8bc4_grande.jpg)",
      "src": "//file.hstatic.net/1000275435/file/tram-sushi-so-17-ngo-19-tran-quang-dieu-ha-noi_6f7e40ac2d5b406788a22018d7af8bc4_grande.jpg"
    },
    {
      "type": "paragraph",
      "align": "justify",
      "markdown": "**>>> Đặt bàn ngay tại: ****[Trạm Sushi](tram-sushi-17-ngo-19-tran-quang-dieu)**"
    },
    {
      "type": "heading",
      "level": 2,
      "id": null,
      "align": "justify",
      "markdown": "## **Myojou Otafuku**"
    },
    {
      "type": "paragraph",
      "align": "justify",
      "markdown": "Đến với Myojou Otafuku, khách hàng sẽ có cơ hội trải nghiệm một không gian trẻ trung, thú vị cho những buổi gặp gỡ, hẹn hò. Với khách ruột của Myojou Otafuku, đừng quên thưởng thức một trong số những mẹt ẩm thực hấp dẫn: set cơm cá Sanma, Cơm cá hồi, Cơm thịt gà trứng, Cơm thịt bò nướng, Cơm bò súp hến, Cơm thịt lợn,..."
    },
    {
      "type": "paragraph",
      "align": "justify",
      "markdown": "Bên cạnh đó, với tone màu ấm và kiểu bàn thấp, Myojou Otafuku mang theo phong cách Nhật Bản đến với từng thực khách. Vừa trải nghiệm thực đơn hấp dẫn, vừa tận hưởng không gian thu hút của **quán Nhật **này chắc chắn sẽ để lại ấn tượng mạnh mẽ cho các thực khách."
    },
    {
      "type": "image",
      "align": "center",
      "markdown": "![](//file.hstatic.net/1000275435/file/quan-an-nhat-tai-ha-noi-myojou-otafuku_e107703b1bb54b159ed8e78b1d1528cb_grande.jpg)",
      "src": "//file.hstatic.net/1000275435/file/quan-an-nhat-tai-ha-noi-myojou-otafuku_e107703b1bb54b159ed8e78b1d1528cb_grande.jpg"
    },
    {
      "type": "paragraph",
      "align": "justify",
      "markdown": "**>>> Đặt bàn ngay tại: ****[Myojou Otafuku](myojou-otafuku-116a-linh-lang)**"
    },
    {
      "type": "heading",
      "level": 2,
      "id": null,
      "align": "justify",
      "markdown": "## **Umai29**"
    },
    {
      "type": "paragraph",
      "align": "justify",
      "markdown": "Tọa lạc tại số 123 Trung Kính, Cầu Giấy, Hà Nội, Nhà hàng Umai29 lâu đã trở thành cái tên khá quen thuộc đối với những tín đồ ẩm thực Nhật. Khi đến nhà hàng, thực khách sẽ được trải nghiệm vô số những món ăn chuẩn hương vị Nhật Bản đầy hấp dẫn đã tạo nên tên tuổi cho nhà hàng."
    },
    {
      "type": "paragraph",
      "align": "justify",
      "markdown": "Ngoài ra, không gian nhà hàng được bài trí vô cùng độc đáo cho phép người đầu bếp và thực khách có thể tương tác với nhau. Với mức giá khoảng 50.000 - 100.000đ/người, Nhà hàng rất thích hợp cho những dịp gặp gỡ, đi ăn cùng bạn bè, gia đình hay những bữa tiệc liên hoan cuối năm."
    },
    {
      "type": "image",
      "align": "center",
      "markdown": "![](//file.hstatic.net/1000275435/file/quan-nhat-ngon-umai-29_b0901cb4403741fea5a2e5c2123560b7_grande.jpg)",
      "src": "//file.hstatic.net/1000275435/file/quan-nhat-ngon-umai-29_b0901cb4403741fea5a2e5c2123560b7_grande.jpg"
    },
    {
      "type": "heading",
      "level": 2,
      "id": null,
      "align": "justify",
      "markdown": "## **Ramen2go**"
    },
    {
      "type": "paragraph",
      "align": "justify",
      "markdown": "Nhắc đến Ramen2go, thực khách thường bị cuốn hút bởi nét hấp dẫn không thể chối từ của mì tươi Nhật Bản. Trong không gian riêng mang hơi thở Nhật Bản vô cùng độc đáo, lý tưởng cho những buổi gặp gỡ, quây quần, thực khách sẽ được tìm hiểu và khám phá thêm văn hoá đất nước mặt trời mọc trong mỗi món ăn, câu chuyện."
    },
    {
      "type": "paragraph",
      "align": "justify",
      "markdown": "Đặc biệt, **mì tươi Nhật Bản** là món ăn hàng đầu do Ramen2go phục vụ. Nếu mới lần đầu ghé thăm, bạn nhớ tham khảo một số mỳ như: Mì Miso Ramen, Mì Shoyu Ramen, Mì trộn Nhật Bản, Mì trộn chua cay…Bên cạnh đó, cũng đừng quên thử cả món tráng miệng bánh giọt nước mang chất riêng của quán nhé!"
    },
    {
      "type": "image",
      "align": "center",
      "markdown": "![](//file.hstatic.net/1000275435/file/quan-an-nhat-ban-ramen-2go_cbdc44d7aaeb4b078f94f983cb6085f6_grande.jpg)",
      "src": "//file.hstatic.net/1000275435/file/quan-an-nhat-ban-ramen-2go_cbdc44d7aaeb4b078f94f983cb6085f6_grande.jpg"
    },
    {
      "type": "heading",
      "level": 2,
      "id": null,
      "align": "justify",
      "markdown": "## **Donkin**"
    },
    {
      "type": "paragraph",
      "align": "justify",
      "markdown": "Đúng như tiêu đề, mức giá ở Donkin vô cùng hợp lý khi rơi vào khoảng 50.000đ - 150.000đ/người. Ngược lại với mức giá phải chăng thì chất lượng món ăn ở đây phải nói trên mức tuyệt vời. Tất cả những món ăn của Donkin đều đậm đà hương vị truyền thống của Nhật Bản, nó có thể chinh phục những vị khách khó tính nhất."
    },
    {
      "type": "paragraph",
      "align": "justify",
      "markdown": "Tọa lạc tại** số 64 Dương Khuê, Mai Dịch, Cầu Giấy**, không gian của Donkin được bài trí vô cùng thoáng đãng, lịch sự, mang hơi hướng của Nhật Bản khi được kết hợp giữa gam màu sáng và đèn treo trần cùng với những bức tranh truyền thống của Nhật."
    },
    {
      "type": "paragraph",
      "align": "justify",
      "markdown": "Muốn tìm một nhà hàng chuẩn Nhật Bản 100% thì hãy ghé ngay đến Donkin!"
    },
    {
      "type": "image",
      "align": "center",
      "markdown": "![](//file.hstatic.net/1000275435/file/dokin-so-64-duong-khue-mai-dich-cau-giay_b12b7c361519433299dfec14adeec2f2_grande.jpg)",
      "src": "//file.hstatic.net/1000275435/file/dokin-so-64-duong-khue-mai-dich-cau-giay_b12b7c361519433299dfec14adeec2f2_grande.jpg"
    },
    {
      "type": "heading",
      "level": 2,
      "id": null,
      "align": "justify",
      "markdown": "## **Shogun Japanese Street BBQ**"
    },
    {
      "type": "paragraph",
      "align": "justify",
      "markdown": "Shogun Japanese Street BBQ là quán ăn thuộc hệ thống Golden Gate, chuyên phục vụ các món nướng mang đậm tinh hoa ẩm thực Nhật Bản. Shogun mang phong cách quán Izakaya - **quán nhậu Nhật** nơi người ta thường ghé đến sau những giờ làm việc căng thẳng để thư giãn cùng bạn bè, giao lưu với đồng nghiệp."
    },
    {
      "type": "paragraph",
      "align": "justify",
      "markdown": "Tại Shogun, các thực khách sẽ được thưởng thức các món ăn nướng nhậu Izakaya đặc trưng của Nhật Bản**.** Đặc biệt, Shogun nổi tiếng với combo nướng đặc biệt sẽ khiến bạn không thể cưỡng lại như Diềm bụng bò Mỹ, Sườn non, Dẻ sườn bò Mỹ… cho tới các loại hải sản như: Bạch tuộc, mực, tôm sú…"
    },
    {
      "type": "paragraph",
      "align": "justify",
      "markdown": "Bên cạnh đó, với không gian rộng rãi, thoải mái, cùng thiết kế mới lạ với toàn bộ nội thất được nhập khẩu từ Nhật, ghế ngồi làm bằng két bia Sapporo tạo cảm cảm giác dân dã, bình dị. Shogun như một con phố của xứ sở mặt trời mọc nằm ngay trong lòng thành Hà Nội. Bên cạnh đó, nhân viên phục vụ ở đây luôn chu đáo, nhiệt tình đảm bảo mang tới trải nghiệm hoàn hảo cho mỗi khách hàng."
    },
    {
      "type": "image",
      "align": "center",
      "markdown": "![](//file.hstatic.net/1000275435/file/shogun-japanese-street-bbq-10-dich-vong-hau_ba83d86ce8744362b468888d3d23709e_grande.jpg)",
      "src": "//file.hstatic.net/1000275435/file/shogun-japanese-street-bbq-10-dich-vong-hau_ba83d86ce8744362b468888d3d23709e_grande.jpg"
    },
    {
      "type": "heading",
      "level": 2,
      "id": null,
      "align": "justify",
      "markdown": "## **Nanami Ramen**"
    },
    {
      "type": "paragraph",
      "align": "justify",
      "markdown": "Với mức giá chỉ 120.000 đ/người, làm sao để trải nghiệm được trọn vẹn ẩm thực Nhật Bản? Nhà hàng Nanami là câu trả lời hoàn hảo cho bạn với đặc trưng “ngon-bổ-rẻ” và vẫn đậm chất Nhật Bản. Đừng quên thưởng thức ngay các món mỳ thơm ngon Mì ramen vị cay Tantan, Mỳ ramen vị nước cốt xương, Mì xá xíu Udon..."
    },
    {
      "type": "paragraph",
      "align": "justify",
      "markdown": "Không gian nhà hàng Nanami được lấy cảm hứng từ quán mỳ nhỏ, tuy không quá rộng rãi nhưng lại là cơ hội tuyệt vời gắn kết hội bạn thân. Đặc biệt, không gian nhà hàng còn là địa điểm lý cho những buổi tụ tập cạ cứng hay hẹn hò cùng người yêu."
    },
    {
      "type": "image",
      "align": "center",
      "markdown": "![](//file.hstatic.net/1000275435/file/10_nhat_re_nhat-10_af6bd06e5b03467293e5064b254dc283_grande_dffc05a55dda47e794571fd3bbf027b1_grande.jpg)",
      "src": "//file.hstatic.net/1000275435/file/10_nhat_re_nhat-10_af6bd06e5b03467293e5064b254dc283_grande_dffc05a55dda47e794571fd3bbf027b1_grande.jpg"
    },
    {
      "type": "paragraph",
      "align": "justify",
      "markdown": "**>>> Đặt bàn ngay tại: ****[Nanami Ramen](nanami-ramen-74-phan-ke-binh)**"
    },
    {
      "type": "paragraph",
      "align": "justify",
      "markdown": "Hãy liên hệ PATO theo hotline [**1900.2280**](tel:19002280) ngay để đặt bàn một cách nhanh chóng nhất!"
    },
    {
      "type": "paragraph",
      "align": "justify",
      "markdown": "➖"
    },
    {
      "type": "paragraph",
      "align": "justify",
      "markdown": "**PATO - KÊNH THÔNG TIN VÀ NỀN TẢNG ĐẶT BÀN NHÀ HÀNG**"
    },
    {
      "type": "paragraph",
      "align": "justify",
      "markdown": "✯ Hotline: [**1900.2280**](tel:19002280)"
    },
    {
      "type": "paragraph",
      "align": "justify",
      "markdown": "✯ Inbox: **[m.me/pato.com.vn](http://m.me/pato.com.vn)**"
    },
    {
      "type": "paragraph",
      "align": "justify",
      "markdown": "✯ Website: **[pato.com.vn](http://m.me/pato.com.vn)**"
    }
  ],
  "related_articles": {
    "title": "Các bài viết liên quan",
    "items": [
      {
        "title": "Danh Sách Nhà Hàng Ngon – View Đẹp – Giá Hợp Lý Trong Vincom Mega Mall Smart City",
        "url": "/blogs/top-nha-hang/danh-sach-nha-hang-ngon-view-dep-gia-hop-ly-trong-vincom-mega-mall"
      },
      {
        "title": "Ăn Gì Ở Vincom Ocean Park? Khám Phá Ẩm Thực Đỉnh Cao Trong Vincom Mega Mall",
        "url": "/blogs/top-nha-hang/an-gi-o-vincom-ocean-park-kham-pha-am-thuc-dinh-cao-trong-vincom-mega"
      },
      {
        "title": "Khám Phá Vương Quốc Ẩm Thực Tại Vincom Mega Mall Royal City Phần 1",
        "url": "/blogs/top-nha-hang/kham-pha-vuong-quoc-am-thuc-tai-vincom-mega-mall-royal-city-phan-1"
      },
      {
        "title": "Khám Phá Ngay Thiên Đường Ẩm Thực Tại Savico Mega Mall Long Biên",
        "url": "/blogs/top-nha-hang/kham-pha-ngay-thien-duong-am-thuc-tai-savico-mega-mall-long-bien"
      },
      {
        "title": "Hành Trình Ẩm Thực Đầy Hấp Dẫn Ở Lotte Mall West Lake Hanoi Phần 3",
        "url": "/blogs/top-nha-hang/hanh-trinh-am-thuc-day-hap-dan-o-lotte-mall-west-lake-hanoi-phan-3"
      },
      {
        "title": "Hành Trình Ẩm Thực Đầy Hấp Dẫn Ở Lotte Mall West Lake Hanoi Phần 2",
        "url": "/blogs/top-nha-hang/hanh-trinh-am-thuc-day-hap-dan-o-lotte-mall-west-lake-hanoi-phan-2"
      }
    ]
  }
}