{
  "slug": "top-nhung-quan-nhau-chat-det-ben-moi-khong-the-bo-qua-tai-ha-noi",
  "title": "Top Những Quán Nhậu Chất Đét, \"Bén Mồi\" Không Thể Bỏ Qua Tại Hà Nội",
  "date": "24/04/26",
  "blocks": [
    {
      "type": "paragraph",
      "align": "justify",
      "markdown": "Văn hóa bia hơi, nhậu nhẹt từ lâu đã trở thành một nét đặc trưng không thể thiếu của người dân Hà Thành. Nếu bạn đang tìm kiếm một địa điểm để cùng \"chiến hữu\" lai rai sau giờ làm hay tụ tập bạn bè vào cuối tuần, hãy tham khảo ngay danh sách những quán nhậu cực chất dưới đây."
    },
    {
      "type": "heading",
      "level": 2,
      "id": null,
      "align": "justify",
      "markdown": "## **Vị Bia **"
    },
    {
      "type": "paragraph",
      "align": "justify",
      "markdown": "Dù là \"tân binh\" nhưng **[Vị Bia 275 Đội Cấn](vi-bia-275-doi-can)** đã nhanh chóng chiếm trọn cảm tình của giới trẻ Hà Thành nhờ sự kết hợp giữa món ăn truyền thống và các món hot-trend. Quán sở hữu không gian 2 tầng rộng rãi, có cả bàn ngồi và bàn bệt linh hoạt với sức chứa 100 khách. Thực đơn tại Vị Bia vô cùng đa dạng, từ món chính như Lẩu cua cà ra, Tôm bỏ lò phô mai đến những món lai rai độc đáo như Kê mề trứng non cháy tỏi, Nộm hải sản Thái. Với cam kết nguồn nguyên liệu sạch, có chứng nhận an toàn thực phẩm và mức giá từ 200.000 – 300.000 VNĐ/người, Vị Bia hứa hẹn mang đến trải nghiệm nhậu \"chất lượng\" cho mọi thực khách."
    },
    {
      "type": "image",
      "align": "center",
      "markdown": "![](//cdn.hstatic.net/1000275435/file/78_cb87433871e840c891dff1aa8b66a0c2_1024x1024.png)",
      "src": "//cdn.hstatic.net/1000275435/file/78_cb87433871e840c891dff1aa8b66a0c2_1024x1024.png"
    },
    {
      "type": "paragraph",
      "align": "center",
      "markdown": "*Mẹt đồ ăn trình bày đẹp mắt tại Vị Bia Đội Cấn – sự kết hợp tinh tế giữa phong cách hiện đại và hương vị dân dã.*"
    },
    {
      "type": "paragraph",
      "align": "justify",
      "markdown": "***>>> Thưởng thức menu nhậu đa dạng, đậm vị quê hương trong không gian ấm cúng – gọi ngay [1900.2280](tel: 19002280) để đặt bàn và nhận ưu đãi giảm 10%***"
    },
    {
      "type": "heading",
      "level": 2,
      "id": null,
      "align": "justify",
      "markdown": "## **Bia Lan Chín **"
    },
    {
      "type": "paragraph",
      "align": "justify",
      "markdown": "Bia Lan Chín cơ sở Tăng Bạt Hổ là cái tên đã quá đỗi quen thuộc với dân sành nhậu Hà Nội. Nhà hàng sở hữu không gian rộng lớn, thiết kế tối giản mang lại cảm giác gần gũi, thân thuộc với sức chứa lên đến 150 người. Thực khách đến đây sẽ bị choáng ngợp bởi thực đơn hơn 100 món ăn truyền thống, nổi bật nhất là các món Tôm sú chiên bơ tỏi thơm lừng, Cá chép chiên giòn, Chả rươi giàu dinh dưỡng hay Thịt dải lợn mềm ngọt. Với mức giá bình dân chỉ từ 200.000 – 300.000 VNĐ/người, đây chính là tọa độ lý tưởng cho những buổi liên hoan, sinh nhật sôi động."
    },
    {
      "type": "image",
      "align": "center",
      "markdown": "![](//cdn.hstatic.net/1000275435/file/79_1d71655fea73420796ec9cb8d910b757_1024x1024.png)",
      "src": "//cdn.hstatic.net/1000275435/file/79_1d71655fea73420796ec9cb8d910b757_1024x1024.png"
    },
    {
      "type": "paragraph",
      "align": "center",
      "markdown": "*Bàn tiệc đầy đặn tại Bia Lan Chín – nơi lưu giữ hương vị ẩm thực truyền thống Hà Thành qua hàng thập kỷ.*"
    },
    {
      "type": "heading",
      "level": 2,
      "id": null,
      "align": "justify",
      "markdown": "## **Bia Hải Hói **"
    },
    {
      "type": "paragraph",
      "align": "justify",
      "markdown": "Nếu bạn muốn khám phá văn hóa bia hơi \"có một không hai\" của thủ đô, Bia Hải Hói tại đường Lê Duẩn là điểm đến không thể bỏ lỡ. Điểm cộng lớn nhất của quán là không gian cực kỳ rộng rãi, thoáng đãng với sức chứa ấn tượng lên đến 500 khách, mang đậm bầu không khí nhộn nhịp đặc trưng của Hà Nội. Thực đơn của quán là sự kết hợp hoàn hảo giữa các món đặc sản vùng miền như Lợn sữa quay, Cá lăng sông Đà nướng, Má heo giòn bì và Nghé xào măng trúc. Mức giá tại đây rất hợp lý, dao động từ 200.000 – 300.000 VNĐ/người, phù hợp cho mọi dịp từ họp mặt gia đình đến tổ chức tiệc công ty quy mô lớn."
    },
    {
      "type": "image",
      "align": "center",
      "markdown": "![](//cdn.hstatic.net/1000275435/file/82_eb10b2264b0341339709dada9de3e6b0_1024x1024.png)",
      "src": "//cdn.hstatic.net/1000275435/file/82_eb10b2264b0341339709dada9de3e6b0_1024x1024.png"
    },
    {
      "type": "paragraph",
      "align": "center",
      "markdown": "*Đại tiệc nhậu thịnh soạn tại Bia Hải Hói với thực đơn hải sản phong phú, đáp ứng mọi khẩu vị của các chiến hữu.*"
    },
    {
      "type": "heading",
      "level": 2,
      "id": null,
      "align": "justify",
      "markdown": "## **Bia 38 **"
    },
    {
      "type": "paragraph",
      "align": "justify",
      "markdown": "Nằm tại KĐT Nam An Khánh, Hoài Đức, **[Bia 38](bia-38-kdt-nam-an-khanh)** được ví như thiên đường lai rai chuẩn vị đồng quê giữa lòng phố thị. Không gian quán được thiết kế mộc mạc, rộng rãi và thoáng mát, rất thích hợp cho những cuộc nhậu cuối ngày hay tụ tập anh em đồng nghiệp. Nhà hàng nức tiếng với các món đặc sản từ dê và đồ đồng quê Bắc Bộ như Dê xào lăn thơm cay, Lẩu dê thuốc bắc thanh ngọt, Chạch ôm chuối đậu hay Nghé nhúng mẻ chua dịu. Chỉ với khoảng 250.000 – 300.000 VNĐ/người, bạn đã có thể thưởng thức một bữa tiệc đầy đặn, đậm đà khó quên."
    },
    {
      "type": "image",
      "align": "center",
      "markdown": "![](//cdn.hstatic.net/1000275435/file/81_ba8325c4220741228a12f5e7d2759165_1024x1024.png)",
      "src": "//cdn.hstatic.net/1000275435/file/81_ba8325c4220741228a12f5e7d2759165_1024x1024.png"
    },
    {
      "type": "paragraph",
      "align": "center",
      "markdown": "*Mẹt hải sản và đồ nhúng tươi ngon tại Bia 38 – sự lựa chọn hoàn hảo cho những bữa tiệc lẩu lai rai cuối tuần.*"
    },
    {
      "type": "paragraph",
      "align": "justify",
      "markdown": "***>>> Thưởng thức đặc sản đồng quê bến bia trong không gian ấm cúng – gọi ngay [1900.2280](tel: 19002280) để đặt bàn.***"
    },
    {
      "type": "heading",
      "level": 2,
      "id": null,
      "align": "justify",
      "markdown": "## **Bia Hơi - 24 Núi Trúc**"
    },
    {
      "type": "paragraph",
      "align": "justify",
      "markdown": "Nằm trên con phố Núi Trúc sầm uất, **[Bia Hơi 24 Núi Trúc](bia-hoi-24-nui-truc)** là điểm hẹn quen thuộc cho những ai yêu thích không khí quán bia truyền thống: đơn giản, gần gũi và nhộn nhịp. Quán có không gian thoáng, dễ ngồi, cực kỳ phù hợp để xả stress sau giờ làm việc. Thực đơn tại đây tập trung vào các món nhậu dân dã, dễ ăn và hợp vị số đông như Lẩu bò đậm đà, Lẩu gà nấm thanh ngọt hay Thịt ba chỉ gác bếp đậm chất Tây Bắc. Với mức giá cực kỳ \"mềm\", chỉ từ 100.000 – 200.000 VNĐ/người, đây là lựa chọn số 1 cho các nhóm bạn sinh viên hoặc dân văn phòng muốn tìm nơi nhậu ngon – bổ – rẻ."
    },
    {
      "type": "image",
      "align": "center",
      "markdown": "![](//cdn.hstatic.net/1000275435/file/80_aa86eb72fb3a4f0b814300b83a07c353_1024x1024.png)",
      "src": "//cdn.hstatic.net/1000275435/file/80_aa86eb72fb3a4f0b814300b83a07c353_1024x1024.png"
    },
    {
      "type": "paragraph",
      "align": "center",
      "markdown": "*Góc nhậu vỉa hè quen thuộc tại Bia hơi 24 Núi Trúc với cốc bia mát lạnh và đĩa chả rươi thơm nức lòng.*"
    },
    {
      "type": "paragraph",
      "align": "justify",
      "markdown": "***>>> Thưởng thức cốc bia mát lạnh cùng mồi ngon trong không gian ấm cúng – gọi ngay [1900.2280](tel: 19002280) để đặt bàn ngay. ***"
    },
    {
      "type": "paragraph",
      "align": "justify",
      "markdown": "Mỗi quán nhậu tại Hà Nội đều mang một phong cách riêng, từ sự nhộn nhịp, quy mô của Bia Hải Hói đến nét hiện đại, trẻ trung của Vị Bia. Hy vọng danh sách này đã giúp bạn tìm được \"tọa độ\" ưng ý để cùng bạn bè nâng ly. Chúc bạn có những cuộc vui trọn vẹn và đừng quên ghé **[PATO](https://pato.com.vn/)** để khám phá thêm những tọa độ ăn uống hot hit tại Hà Nội nhé!"
    }
  ],
  "related_articles": {
    "title": "Các bài viết liên quan",
    "items": [
      {
        "title": "Top 5 quán hải sản ngon Sài Gòn 2026: Tươi rói, đậm đà, \"oanh tạc\" mọi buổi nhậu",
        "url": "/blogs/blog-pato/top-5-quan-hai-san-ngon-sai-gon-2026-tuoi-roi-dam-da-oanh-tac-moi"
      },
      {
        "title": "Top 5 mỹ vị Gia Lâm: Từ đồ Nhật thượng hạng đến lẩu Thái cay nồng chuẩn vị",
        "url": "/blogs/blog-pato/top-5-my-vi-gia-lam-tu-do-nhat-thuong-hang-den-lau-thai-cay-nong-chua"
      },
      {
        "title": "Top Những Quán Gà Ngon Nức Tiếng Không Thể Bỏ Lỡ Tại Hà Nội",
        "url": "/blogs/blog-pato/top-nhung-quan-ga-ngon-nuc-tieng-khong-the-bo-lo-tai-ha-noi"
      },
      {
        "title": "Top 5 Quán Sushi Và Ẩm Thực Nhật Bản Đáng Thử Nhất Tại Hà Nội",
        "url": "/blogs/blog-pato/top-5-quan-sushi-va-am-thuc-nhat-ban-dang-thu-nhat-tai-ha-noi"
      },
      {
        "title": "Top 5 \"thiên đường\" đồ Thái quận Cầu Giấy: Vị chuẩn xứ Chùa Vàng, ngon quên lối về!",
        "url": "/blogs/blog-pato/top-5-thien-duong-do-thai-quan-cau-giay-vi-chuan-xu-chua-vang-ngon"
      }
    ]
  }
}